aas_job_register_downloader/__init__.py
aas_job_register_downloader/cli.py
aas_job_register_downloader/html_parser.py
aas_job_register_downloader/parse_job_page.py
aas_job_register_downloader/parse_main_page.py
aas_job_register_downloader-1.1.dist-info/METADATA
aas_job_register_downloader-1.1.dist-info/WHEEL
aas_job_register_downloader-1.1.dist-info/entry_points.txt
aas_job_register_downloader-1.1.dist-info/top_level.txt
aas_job_register_downloader-1.1.dist-info/zip-safe
aas_job_register_downloader-1.1.dist-info/RECORD
