Metadata-Version: 2.1
Name: aas-job-register-downloader
Version: 1.1
Summary: Download a CSV version of the AAS job table.
Home-page: https://github.com/avivajpeyi/aas_job_register_downloader
Author: Avi Vajpeyi
Author-email: avi.vajpeyi@gmail.com
Maintainer: Avi Vajpeyi
Maintainer-email: avi.vajpeyi@gmail.com
License: MIT
Platform: UNKNOWN
Classifier: Development Status :: 5 - Production/Stable
Classifier: Intended Audience :: Developers
Classifier: Intended Audience :: Science/Research
Classifier: License :: OSI Approved :: MIT License
Classifier: Operating System :: OS Independent
Classifier: Programming Language :: Python
Classifier: Programming Language :: Python :: 3
Requires-Dist: beautifulsoup4
Requires-Dist: pandas
Requires-Dist: requests
Requires-Dist: tqdm
Provides-Extra: dev
Requires-Dist: pytest (>=3.6) ; extra == 'dev'
Requires-Dist: pre-commit ; extra == 'dev'
Requires-Dist: flake8 ; extra == 'dev'
Requires-Dist: black ; extra == 'dev'
Requires-Dist: isort ; extra == 'dev'
Provides-Extra: test
Requires-Dist: pytest (>=3.6) ; extra == 'test'
